{"start":{"cells":[[{"cellType":"Void","objects":[]},{"cellType":"Void","objects":[]},{"cellType":"Void","objects":[]},{"cellType":"Void","objects":[]},{"cellType":"Void","objects":[]},{"cellType":"Void","objects":[]},{"cellType":"Void","objects":[]}],[{"cellType":"Void","objects":[]},{"cellType":"Wall","objects":[]},{"cellType":"Void","objects":[]},{"cellType":"Void","objects":[]},{"cellType":"Void","objects":[]},{"cellType":"Void","objects":[]},{"cellType":"Void","objects":[]}],[{"cellType":"Void","objects":[]},{"cellType":"Floor","objects":[]},{"cellType":"Floor","objects":[]},{"cellType":"Floor","objects":[{"type":"Goal","id":"goal-1"}]},{"cellType":"Void","objects":[]},{"cellType":"Void","objects":[]},{"cellType":"Void","objects":[]}],[{"cellType":"Void","objects":[]},{"cellType":"Void","objects":[]},{"cellType":"Void","objects":[{"type":"Barrier","id":"barrier-1"}]},{"cellType":"Void","objects":[{"type":"Barrier","id":"barrier-2"}]},{"cellType":"Void","objects":[{"type":"Barrier","id":"barrier-3"}]},{"cellType":"Void","objects":[]},{"cellType":"Void","objects":[]}],[{"cellType":"Void","objects":[]},{"cellType":"Void","objects":[]},{"cellType":"Void","objects":[]},{"cellType":"Void","objects":[]},{"cellType":"Void","objects":[]},{"cellType":"Void","objects":[]},{"cellType":"Void","objects":[]}],[{"cellType":"Void","objects":[]},{"cellType":"Void","objects":[]},{"cellType":"Void","objects":[]},{"cellType":"Floor","objects":[]},{"cellType":"Floor","objects":[]},{"cellType":"Wall","objects":[]},{"cellType":"Void","objects":[]}],[{"cellType":"Void","objects":[]},{"cellType":"Void","objects":[]},{"cellType":"Floor","objects":[{"type":"Player","id":"player-1"}]},{"cellType":"Floor","objects":[]},{"cellType":"Floor","objects":[{"type":"Player Two","id":"player-two-1"}]},{"cellType":"Void","objects":[]},{"cellType":"Void","objects":[]}],[{"cellType":"Void","objects":[]},{"cellType":"Floor","objects":[]},{"cellType":"Floor","objects":[]},{"cellType":"Floor","objects":[]},{"cellType":"Floor","objects":[]},{"cellType":"Void","objects":[]},{"cellType":"Void","objects":[]}],[{"cellType":"Void","objects":[]},{"cellType":"Void","objects":[]},{"cellType":"Void","objects":[]},{"cellType":"Void","objects":[]},{"cellType":"Void","objects":[]},{"cellType":"Void","objects":[]},{"cellType":"Void","objects":[]}]],"topY":0,"leftX":0}}